earthdata_hashdiff/__about__.py
earthdata_hashdiff/__init__.py
earthdata_hashdiff/compare.py
earthdata_hashdiff/generate.py
earthdata_hashdiff-1.2.0.dist-info/METADATA
earthdata_hashdiff-1.2.0.dist-info/WHEEL
earthdata_hashdiff-1.2.0.dist-info/licenses/LICENSE
earthdata_hashdiff-1.2.0.dist-info/RECORD
