Metadata-Version: 2.4
Name: earthdata-hashdiff
Version: 1.2.0
Summary: Python package that hashes content of Earth science data files and compares to reference files.
Project-URL: Documentation, https://github.com/nasa/earthdata-hashdiff#readme
Project-URL: Issues, https://github.com/nasa/earthdata-hashdiff/issues
Project-URL: Source, https://github.com/nasa/earthdata-hashdiff
Author-email: Owen Littlejohns <owen.m.littlejohns@nasa.gov>, Matt Savoie <savoie@colorado.edu>
Maintainer-email: Owen Littlejohns <owen.m.littlejohns@nasa.gov>, Matt Savoie <savoie@colorado.edu>
License-File: LICENSE
Classifier: License :: OSI Approved :: Apache Software License
Classifier: Operating System :: OS Independent
Classifier: Programming Language :: Python :: 3
Classifier: Programming Language :: Python :: 3.11
Classifier: Programming Language :: Python :: 3.12
Requires-Python: >=3.11
Requires-Dist: netcdf4~=1.7.2
Requires-Dist: numpy~=2.2.3
Requires-Dist: tifffile~=2025.6.11
Requires-Dist: xarray~=2025.6.1
